{
 "_type": "song",
 "annotation_count": 26,
 "api_path": "/songs/9802397",
 "artist_names": "Lyrical Lemonade & Dave (Ft. Jack Harlow)",
 "full_title": "Stop Giving Me Advice by\u00a0Lyrical\u00a0Lemonade & Dave (Ft.\u00a0Jack\u00a0Harlow)",
 "header_image_thumbnail_url": "https://images.genius.com/702fc7d3565aceb48a4879749062ddda.300x300x1.png",
 "header_image_url": "https://images.genius.com/702fc7d3565aceb48a4879749062ddda.1000x1000x1.png",
 "id": 9802397,
 "instrumental": false,
 "lyrics_owner_id": 5748418,
 "lyrics_state": "complete",
 "lyrics_updated_at": 1715859683,
 "path": "/Lyrical-lemonade-and-dave-stop-giving-me-advice-lyrics",
 "primary_artist_names": "Lyrical Lemonade & Dave",
 "pyongs_count": 1,
 "relationships_index_url": "https://genius.com/Lyrical-lemonade-and-dave-stop-giving-me-advice-sample",
 "release_date_components": {
  "year": 2023,
  "month": 12,
  "day": 8
 },
 "release_date_for_display": "December 8, 2023",
 "release_date_with_abbreviated_month_for_display": "Dec. 8, 2023",
 "song_art_image_thumbnail_url": "https://images.genius.com/702fc7d3565aceb48a4879749062ddda.300x300x1.png",
 "song_art_image_url": "https://images.genius.com/702fc7d3565aceb48a4879749062ddda.1000x1000x1.png",
 "stats": {
  "unreviewed_annotations": 19,
  "hot": false,
  "pageviews": 75323
 },
 "title": "Stop Giving Me Advice",
 "title_with_featured": "Stop Giving Me Advice (Ft.\u00a0Jack\u00a0Harlow)",
 "updated_by_human_at": 1718064823,
 "url": "https://genius.com/Lyrical-lemonade-and-dave-stop-giving-me-advice-lyrics",
 "featured_artists": [
  {
   "_type": "artist",
   "api_path": "/artists/615747",
   "header_image_url": "https://images.genius.com/8d518a2457aea7a523276ff6e8832cf0.1000x313x1.jpg",
   "id": 615747,
   "image_url": "https://images.genius.com/6ab01e566d54299478dbcda158f6f396.1000x1000x1.jpg",
   "index_character": "j",
   "is_meme_verified": false,
   "is_verified": true,
   "name": "Jack Harlow",
   "slug": "Jack-harlow",
   "url": "https://genius.com/artists/Jack-harlow",
   "iq": 4362
  }
 ],
 "primary_artist": {
  "_type": "artist",
  "api_path": "/artists/3758173",
  "header_image_url": "https://images.genius.com/34c0e70e7d187c72b2db735427873517.820x820x1.jpg",
  "id": 3758173,
  "image_url": "https://images.genius.com/34c0e70e7d187c72b2db735427873517.820x820x1.jpg",
  "index_character": "l",
  "is_meme_verified": false,
  "is_verified": false,
  "name": "Lyrical Lemonade & Dave",
  "slug": "Lyrical-lemonade-and-dave",
  "url": "https://genius.com/artists/Lyrical-lemonade-and-dave"
 },
 "primary_artists": [
  {
   "_type": "artist",
   "api_path": "/artists/3758173",
   "header_image_url": "https://images.genius.com/34c0e70e7d187c72b2db735427873517.820x820x1.jpg",
   "id": 3758173,
   "image_url": "https://images.genius.com/34c0e70e7d187c72b2db735427873517.820x820x1.jpg",
   "index_character": "l",
   "is_meme_verified": false,
   "is_verified": false,
   "name": "Lyrical Lemonade & Dave",
   "slug": "Lyrical-lemonade-and-dave",
   "url": "https://genius.com/artists/Lyrical-lemonade-and-dave"
  }
 ],
 "artist": "Lyrical Lemonade & Dave",
 "lyrics": "75 ContributorsTranslationsDeutschStop Giving Me Advice Lyrics[Intro: Jack Harlow]\nBom, bom, bom, bom\nHuh\n\n[Verse 1: Jack Harlow]\nHave you ever raised the value of everyone around you?\nHave you ever been so high they got to down you?\nThink pieces gettin' written about you\nHave you ever been to Italy and eaten Italian?\nHave you ever signed a deal that came with a medallion?\nHave you ever booked the club and came with a battalion?\nHave you been to Montana and seen the mountains?\nHave you ever looked around and felt the profound sense of pride?\nHave you ever had to hide where exactly you reside?\nHave you been to the Waffle House on Northside?\nHave you ever made a popstar wanna be your bride?\nHave you hugged someone and they cried?\nHave you had your heroes sit you down and give you the guide?\nHave you ever spoken somethin' into existence\nOr do you just talk about other people's lives?\n\n[Chorus: Jack Harlow]\nStop givin' me advice (Bom, bom, bom, bom)\nStop givin' me, tsch\nStop givin' me advice\nStop\nYou might also like[Verse 2: Jack Harlow]\nAll this unsolicited advice from the guys gettin' booked for a quarter of my price\nAll this red carpet shit, brand partnerships, I must've let y'all forget that boy nice\nNo Sprite, but life givin' me lemons with the limelight (Bom, bom, bom, bom)\nIt's fine, victory's mine\nI lost the desire for bein' intimate at the end of my nights\nI can do that at the end of my life\nYou know the phrase is \"Business before pleasure\"\n'Cause I'm bankin' on it bringin' me more pleasure\nThe pressure makes diamonds, and diamonds make more pressure\nAnd so on and so forth, okay, I'll give your four more measures\nAnd more records with more effort than ever before\nI'm the youngin' on the team that's got a veteran core\nThey know the formula, just give him space and let him record\nAnd just remember what he said on the chorus\n\n[Chorus: Jack Harlow & Dave]\nStop givin' me advice (Bom, bom, bom, bom)\nStop givin' me, tsch\nStop givin' me advice\nStop\nStop givin' me advice (Yeah)\nStop givin' me, tsch (Yeah)\nStop givin' me advice (Yeah)\nStop\n[Verse 3: Dave]\nI know you feel love, feel shame, feel pride, I can see it in your eyes\nI met a fan at work, he told me it's his job on the side\nAs if I'm unimpressed by his everyday life\nNiggas die every day, B, that's everyday life\nThe women that you idolise can never play wife to me\nWhen you done as many flights as me, long nights as me\nTook as many left turns to make right as me\nI'm in the middle of the Vale like a bride to be, that's why I like to (Bom, bom, bom, bom)\nYeah, you left somebody that you love at the bottom of a mountain\nCah they afraid to climb it, have you changed your climate?\nHad her Insta' and made her change to private?\nHad her fly economy and make her change to private?\nSeen your nigga get nicked, and then go and catch a case just like him?\nBrought her to the game and she ain't excited\nProbably cah my mum sat courtside 'fore I did\nAm I sick if I say I like women with mileage and trips to Knightsbridge?\nOh, Jemima, trips in the park with my oldest rider\nTo test out the .9 like I loaned a striker\nI'm a lone survivor, and the way I spell lone is A-L-O-A-N\nI don't ever wanna spend on a ho again\nBut I'm a fuckin' feminist, so I go again\nI'm on the road again, yeah (Bom, bom, bom, bom)\nYou can't control what the heart feels\nYou soon go broke, I see you blowin' it fast still\nDeath row, you niggas down to your last meal\nYou ever signed a seven-figure deal in a bird's quill?\nCan't even call it breakfast cah it wasn't your first mill'\nForgotten birthdays, but remember your verse still, yeah\nYou ever fucked a super model and it sounds like skeletons dancin'?\nYou feel numb to the praise and the memories passin'?\nYou ever robbed someone and it sounds like askin'?\nDidn't have no food, so you'd disguise it as fastin'\nHad drugs, abuse perfumes tryna mask it (Bom, bom, bom, bom)\nYou ever lived the life of an artist, escapin' darkness?\nFines and you're payin' for parkin'\nYou can tell how she fuck by the way that she glancin'\nYour communication's bad, but you're rich, so she givin' you chances\nAnd pretty women givin' you dances\nI come with a pope, but she more Olivia than Francis\nYou ever been\n[Chorus: Jack Harlow]\nStop givin' me advice (Bom, bom, bom, bom)\nStop givin' me, tsch\nStop givin' me advice\nStop\nStop givin' me advice\nStop givin' me, tsch\nStop givin' me advice\nStop1Embed"
}