{
 "_type": "song",
 "annotation_count": 14,
 "api_path": "/songs/4221737",
 "artist_names": "The Backseat Lovers",
 "full_title": "Pool House by\u00a0The\u00a0Backseat Lovers",
 "header_image_thumbnail_url": "https://images.genius.com/6035460c980ede77aa66b4b75f868556.300x300x1.jpg",
 "header_image_url": "https://images.genius.com/6035460c980ede77aa66b4b75f868556.500x500x1.jpg",
 "id": 4221737,
 "instrumental": false,
 "lyrics_owner_id": 5247974,
 "lyrics_state": "complete",
 "lyrics_updated_at": 1696227662,
 "path": "/The-backseat-lovers-pool-house-lyrics",
 "primary_artist_names": "The Backseat Lovers",
 "pyongs_count": 6,
 "relationships_index_url": "https://genius.com/The-backseat-lovers-pool-house-sample",
 "release_date_components": {
  "year": 2018,
  "month": 1,
  "day": 26
 },
 "release_date_for_display": "January 26, 2018",
 "release_date_with_abbreviated_month_for_display": "Jan. 26, 2018",
 "song_art_image_thumbnail_url": "https://images.genius.com/6035460c980ede77aa66b4b75f868556.300x300x1.jpg",
 "song_art_image_url": "https://images.genius.com/6035460c980ede77aa66b4b75f868556.500x500x1.jpg",
 "stats": {
  "unreviewed_annotations": 14,
  "hot": false,
  "pageviews": 76655
 },
 "title": "Pool House",
 "title_with_featured": "Pool House",
 "updated_by_human_at": 1696227662,
 "url": "https://genius.com/The-backseat-lovers-pool-house-lyrics",
 "featured_artists": [],
 "primary_artist": {
  "_type": "artist",
  "api_path": "/artists/1608117",
  "header_image_url": "https://images.genius.com/e47a76be65a546291ed344995ab06c9b.1000x421x1.png",
  "id": 1608117,
  "image_url": "https://images.genius.com/45fdf41f7f3ae0cdd0cff38f8648a15a.639x639x1.jpg",
  "index_character": "b",
  "is_meme_verified": false,
  "is_verified": false,
  "name": "The Backseat Lovers",
  "slug": "The-backseat-lovers",
  "url": "https://genius.com/artists/The-backseat-lovers"
 },
 "primary_artists": [
  {
   "_type": "artist",
   "api_path": "/artists/1608117",
   "header_image_url": "https://images.genius.com/e47a76be65a546291ed344995ab06c9b.1000x421x1.png",
   "id": 1608117,
   "image_url": "https://images.genius.com/45fdf41f7f3ae0cdd0cff38f8648a15a.639x639x1.jpg",
   "index_character": "b",
   "is_meme_verified": false,
   "is_verified": false,
   "name": "The Backseat Lovers",
   "slug": "The-backseat-lovers",
   "url": "https://genius.com/artists/The-backseat-lovers"
  }
 ],
 "artist": "The Backseat Lovers",
 "lyrics": "85 ContributorsPool House Lyrics[Intro]\nThis song's called \"Dugout\"\n\"Pool House\"\n\"Pool House\"\nTh-this song's called \"Pool House\"\nOne, two, three, four\n\n[Verse 1]\nWaiting around for something to change my mood\n'Cause I know that what's in this plastic cup isn't going to\nKids on the lawn, stuck in pairs of two\nYour lunch is on its way back up but you're still in the pool\n\n[Chorus]\nWait inside\nI'll be fine\nI guess I'll sit outside\nWhile you change your mind, oh no, woah-oh\n\n[Verse 2]\nI'll risk it all to find\nA place where I can hear my thoughts\nThis song is playing too loud\nBut upstairs they're still making out\nI'm getting all choked up\nI guess it's just my luck\nAnd I'm stuck on the porch\nWhat am I waiting for?\nYou might also like[Chorus]\nWait inside\nI'll be fine\nI guess I'll sit outside\nWhile you change your mind\n\n[Chorus]\nWait inside\nI'll be fine\nWait inside\nChange your mind\nOh, honey, you'll change your mind6Embed"
}